conda_lock/__init__.py
conda_lock/__main__.py
conda_lock/_export_lock_spec_compute_platform_indep.py
conda_lock/click_helpers.py
conda_lock/common.py
conda_lock/conda_lock.py
conda_lock/conda_solver.py
conda_lock/content_hash.py
conda_lock/content_hash_types.py
conda_lock/default-virtual-packages.yaml
conda_lock/errors.py
conda_lock/export_lock_spec.py
conda_lock/invoke_conda.py
conda_lock/lookup.py
conda_lock/lookup_cache.py
conda_lock/pypi_solver.py
conda_lock/tempdir_manager.py
conda_lock/virtual_package.py
conda_lock/_vendor/LICENSES.md
conda_lock/_vendor/README.md
conda_lock/_vendor/__init__.py
conda_lock/_vendor/cleo.LICENSE
conda_lock/_vendor/conda.LICENSE
conda_lock/_vendor/grayskull.pyi
conda_lock/_vendor/poetry.LICENSE
conda_lock/_vendor/poetry_core.LICENSE
conda_lock/_vendor/vendor.txt
conda_lock/_vendor/cleo/LICENSE
conda_lock/_vendor/cleo/__init__.py
conda_lock/_vendor/cleo/_compat.py
conda_lock/_vendor/cleo/_utils.py
conda_lock/_vendor/cleo/application.py
conda_lock/_vendor/cleo/color.py
conda_lock/_vendor/cleo/cursor.py
conda_lock/_vendor/cleo/helpers.py
conda_lock/_vendor/cleo/py.typed
conda_lock/_vendor/cleo/terminal.py
conda_lock/_vendor/cleo/commands/__init__.py
conda_lock/_vendor/cleo/commands/base_command.py
conda_lock/_vendor/cleo/commands/command.py
conda_lock/_vendor/cleo/commands/completions_command.py
conda_lock/_vendor/cleo/commands/help_command.py
conda_lock/_vendor/cleo/commands/list_command.py
conda_lock/_vendor/cleo/commands/completions/__init__.py
conda_lock/_vendor/cleo/commands/completions/templates.py
conda_lock/_vendor/cleo/descriptors/__init__.py
conda_lock/_vendor/cleo/descriptors/application_description.py
conda_lock/_vendor/cleo/descriptors/descriptor.py
conda_lock/_vendor/cleo/descriptors/text_descriptor.py
conda_lock/_vendor/cleo/events/__init__.py
conda_lock/_vendor/cleo/events/console_command_event.py
conda_lock/_vendor/cleo/events/console_error_event.py
conda_lock/_vendor/cleo/events/console_event.py
conda_lock-4.0.0.dist-info/METADATA
conda_lock-4.0.0.dist-info/WHEEL
conda_lock-4.0.0.dist-info/entry_points.txt
conda_lock-4.0.0.dist-info/licenses/LICENSE
conda_lock-4.0.0.dist-info/licenses/conda_lock/_vendor/cleo.LICENSE
conda_lock-4.0.0.dist-info/licenses/conda_lock/_vendor/conda.LICENSE
conda_lock-4.0.0.dist-info/licenses/conda_lock/_vendor/conda/_vendor/appdirs.LICENSE.txt
conda_lock-4.0.0.dist-info/licenses/conda_lock/_vendor/conda/_vendor/distro.LICENSE.txt
conda_lock-4.0.0.dist-info/licenses/conda_lock/_vendor/conda/_vendor/frozendict/LICENSE.txt
conda_lock-4.0.0.dist-info/licenses/conda_lock/_vendor/conda/_vendor/py_cpuinfo.LICENSE
conda_lock-4.0.0.dist-info/licenses/conda_lock/_vendor/conda/auxlib/LICENSE
conda_lock-4.0.0.dist-info/licenses/conda_lock/_vendor/poetry.LICENSE
conda_lock-4.0.0.dist-info/licenses/conda_lock/_vendor/poetry/core/_vendor/fastjsonschema/LICENSE
conda_lock-4.0.0.dist-info/licenses/conda_lock/_vendor/poetry/core/_vendor/lark/LICENSE
conda_lock-4.0.0.dist-info/licenses/conda_lock/_vendor/poetry/core/_vendor/packaging/LICENSE
conda_lock-4.0.0.dist-info/licenses/conda_lock/_vendor/poetry/core/_vendor/packaging/LICENSE.APACHE
conda_lock-4.0.0.dist-info/licenses/conda_lock/_vendor/poetry/core/_vendor/packaging/LICENSE.BSD
conda_lock-4.0.0.dist-info/licenses/conda_lock/_vendor/poetry/core/_vendor/tomli/LICENSE
conda_lock-4.0.0.dist-info/licenses/conda_lock/_vendor/poetry_core.LICENSE
conda_lock-4.0.0.dist-info/RECORD
