Metadata-Version: 2.4
Name: conda_lock
Version: 4.0.0
Summary: Lockfiles for conda
Project-URL: Homepage, https://github.com/conda/conda-lock
Project-URL: Repository, https://github.com/conda/conda-lock
Project-URL: Documentation, https://conda.github.io/conda-lock/
Project-URL: Issue Tracker, https://github.com/conda/conda-lock/issues
Project-URL: Conda-Forge Feedstock, https://github.com/conda-forge/conda-lock-feedstock
Project-URL: Anaconda.org, https://anaconda.org/conda-forge/conda-lock
Author-email: Marius van Niekerk <marius.v.niekerk@gmail.com>
License-Expression: MIT
License-File: LICENSE
License-File: conda_lock/_vendor/cleo.LICENSE
License-File: conda_lock/_vendor/conda.LICENSE
License-File: conda_lock/_vendor/conda/_vendor/appdirs.LICENSE.txt
License-File: conda_lock/_vendor/conda/_vendor/distro.LICENSE.txt
License-File: conda_lock/_vendor/conda/_vendor/frozendict/LICENSE.txt
License-File: conda_lock/_vendor/conda/_vendor/py_cpuinfo.LICENSE
License-File: conda_lock/_vendor/conda/auxlib/LICENSE
License-File: conda_lock/_vendor/poetry.LICENSE
License-File: conda_lock/_vendor/poetry/core/_vendor/fastjsonschema/LICENSE
License-File: conda_lock/_vendor/poetry/core/_vendor/lark/LICENSE
License-File: conda_lock/_vendor/poetry/core/_vendor/packaging/LICENSE
License-File: conda_lock/_vendor/poetry/core/_vendor/packaging/LICENSE.APACHE
License-File: conda_lock/_vendor/poetry/core/_vendor/packaging/LICENSE.BSD
License-File: conda_lock/_vendor/poetry/core/_vendor/tomli/LICENSE
License-File: conda_lock/_vendor/poetry_core.LICENSE
Classifier: Development Status :: 5 - Production/Stable
Classifier: Intended Audience :: Science/Research
Classifier: License :: OSI Approved :: MIT License
Classifier: Operating System :: OS Independent
Classifier: Programming Language :: Python
Classifier: Programming Language :: Python :: 3
Classifier: Programming Language :: Python :: 3.10
Classifier: Programming Language :: Python :: 3.11
Classifier: Programming Language :: Python :: 3.12
Classifier: Programming Language :: Python :: 3.13
Classifier: Programming Language :: Python :: 3.14
Requires-Python: >=3.10
Requires-Dist: boltons>=23.0.0
Requires-Dist: build<2.0.0,>=1.2.1
Requires-Dist: cachecontrol[filecache]<0.15.0,>=0.14.0
Requires-Dist: charset-normalizer
Requires-Dist: click-default-group
Requires-Dist: click>=8.0
Requires-Dist: crashtest<0.5.0,>=0.4.1
Requires-Dist: dulwich<0.25,>=0.22.6
Requires-Dist: ensureconda>=1.4.7
Requires-Dist: fastjsonschema<3.0.0,>=2.18.0
Requires-Dist: filelock
Requires-Dist: gitpython>=3.1.30
Requires-Dist: importlib-metadata>=4.4; python_version < '3.10'
Requires-Dist: installer<0.8.0,>=0.7.0
Requires-Dist: jinja2
Requires-Dist: keyring<26.0.0,>=25.1.0
Requires-Dist: packaging>=24.0
Requires-Dist: pkginfo<2.0,>=1.12
Requires-Dist: platformdirs<5.0.0,>=3.10.0
Requires-Dist: pydantic>=2
Requires-Dist: pyproject-hooks<2.0.0,>=1.0.0
Requires-Dist: pyyaml>=5.1
Requires-Dist: requests-toolbelt<2.0.0,>=1.0.0
Requires-Dist: requests<3.0,>=2.26
Requires-Dist: ruamel-yaml
Requires-Dist: semver<4,>=3
Requires-Dist: setuptools
Requires-Dist: shellingham<2.0,>=1.5
Requires-Dist: tomli<3.0.0,>=2.0.1; python_version < '3.11'
Requires-Dist: tomlkit<1.0.0,>=0.11.4
Requires-Dist: trove-classifiers>=2022.5.19
Requires-Dist: typing-extensions>=4.6.1
Requires-Dist: virtualenv<21.0.0,>=20.26.6
Requires-Dist: xattr<2.0.0,>=1.0.0; sys_platform == 'darwin'
Requires-Dist: zstandard>=0.15
